odoo8_addon_account_invoice_uom-8.0.1.0.0.99.dev15-py2.7-nspkg.pth
odoo8_addon_account_invoice_uom-8.0.1.0.0.99.dev15.dist-info/DESCRIPTION.rst
odoo8_addon_account_invoice_uom-8.0.1.0.0.99.dev15.dist-info/METADATA
odoo8_addon_account_invoice_uom-8.0.1.0.0.99.dev15.dist-info/RECORD
odoo8_addon_account_invoice_uom-8.0.1.0.0.99.dev15.dist-info/WHEEL
odoo8_addon_account_invoice_uom-8.0.1.0.0.99.dev15.dist-info/metadata.json
odoo8_addon_account_invoice_uom-8.0.1.0.0.99.dev15.dist-info/namespace_packages.txt
odoo8_addon_account_invoice_uom-8.0.1.0.0.99.dev15.dist-info/top_level.txt
odoo_addons/account_invoice_uom/README.rst
odoo_addons/account_invoice_uom/__init__.py
odoo_addons/account_invoice_uom/__openerp__.py
odoo_addons/account_invoice_uom/account_invoice_line.py
odoo_addons/account_invoice_uom/account_invoice_line_view.xml
odoo_addons/account_invoice_uom/i18n/bs.po
odoo_addons/account_invoice_uom/i18n/ca.po
odoo_addons/account_invoice_uom/i18n/cs.po
odoo_addons/account_invoice_uom/i18n/de.po
odoo_addons/account_invoice_uom/i18n/es.po
odoo_addons/account_invoice_uom/i18n/es_MX.po
odoo_addons/account_invoice_uom/i18n/fr.po
odoo_addons/account_invoice_uom/i18n/fr_CH.po
odoo_addons/account_invoice_uom/i18n/hr.po
odoo_addons/account_invoice_uom/i18n/hr_HR.po
odoo_addons/account_invoice_uom/i18n/it.po
odoo_addons/account_invoice_uom/i18n/nl_BE.po
odoo_addons/account_invoice_uom/i18n/nl_NL.po
odoo_addons/account_invoice_uom/i18n/pt_BR.po
odoo_addons/account_invoice_uom/i18n/pt_PT.po
odoo_addons/account_invoice_uom/i18n/sl.po
odoo_addons/account_invoice_uom/i18n/tr.po
odoo_addons/account_invoice_uom/i18n/tr_TR.po
odoo_addons/account_invoice_uom/static/description/icon.png
odoo_addons/account_invoice_uom/test/account_invoice_uom.yml
